LICENSE
README.md
pyproject.toml
django_centrifugo/__about__.py
django_centrifugo/__init__.py
django_centrifugo/admin.py
django_centrifugo/apps.py
django_centrifugo/models.py
django_centrifugo/tests.py
django_centrifugo/migrations/0001_initial.py
django_centrifugo/migrations/__init__.py
django_centrifugo-0.1.1.dist-info/METADATA
django_centrifugo-0.1.1.dist-info/WHEEL
django_centrifugo-0.1.1.dist-info/licenses/LICENSE
django_centrifugo-0.1.1.dist-info/RECORD
