Metadata-Version: 2.3
Name: django-centrifugo
Version: 0.1.1
Summary: Implementation of an outbox model for Centrifugo
Project-URL: Documentation, https://github.com/pikhovkin/django-centrifugo#readme
Project-URL: Issues, https://github.com/pikhovkin/django-centrifugo/issues
Project-URL: Source, https://github.com/pikhovkin/django-centrifugo
Author-email: Sergei Pikhovkin <s@pikhovkin.ru>
License: MIT
Keywords: centrifugo,centrifugo-outbox,django,outbox
Classifier: Development Status :: 4 - Beta
Classifier: Environment :: Web Environment
Classifier: Framework :: Django :: 4.0
Classifier: Framework :: Django :: 4.1
Classifier: Framework :: Django :: 4.2
Classifier: Framework :: Django :: 5.0
Classifier: Framework :: Django :: 5.1
Classifier: License :: OSI Approved :: MIT License
Classifier: Operating System :: OS Independent
Classifier: Programming Language :: Python
Classifier: Programming Language :: Python :: 3
Classifier: Programming Language :: Python :: 3 :: Only
Classifier: Programming Language :: Python :: 3.10
Classifier: Programming Language :: Python :: 3.11
Classifier: Programming Language :: Python :: 3.12
Classifier: Programming Language :: Python :: 3.13
Classifier: Topic :: System :: Monitoring
Classifier: Topic :: Utilities
Requires-Python: <3.14,>=3.10
Requires-Dist: django<5.2,>=4.0
